<?xml version="1.0" encoding="UTF-8"?>
<GraphicalSchema xmlns="http://v8.1c.ru/8.3/xcf/scheme" xmlns:sch="http://v8.1c.ru/8.2/data/graphscheme" xmlns:style="http://v8.1c.ru/8.1/data/ui/style" xmlns:v8="http://v8.1c.ru/8.1/data/core" xmlns:v8ui="http://v8.1c.ru/8.1/data/ui" xmlns:web="http://v8.1c.ru/8.1/data/ui/colors/web" xmlns:win="http://v8.1c.ru/8.1/data/ui/colors/windows" xmlns:xs="http://www.w3.org/2001/XMLSchema" xmlns:xsi="http://www.w3.org/2001/XMLSchema-instance" version="2.20">
	<BackColor>style:FieldBackColor</BackColor>
	<GridEnabled>true</GridEnabled>
	<DrawGridMode>Lines</DrawGridMode>
	<GridHorizontalStep>20</GridHorizontalStep>
	<GridVerticalStep>20</GridVerticalStep>
	<PrintParameters>
		<TopMargin>10</TopMargin>
		<LeftMargin>10</LeftMargin>
		<BottomMargin>10</BottomMargin>
		<RightMargin>10</RightMargin>
		<BlackAndWhite>false</BlackAndWhite>
		<FitPageMode>Auto</FitPageMode>
	</PrintParameters>
	<Items>
		<Completion id="1" uuid="fa87c737-d416-4226-b74a-916c018a0278">
			<Properties>
				<Name>Завершение</Name>
				<Title>
					<v8:item>
						<v8:lang>ru</v8:lang>
						<v8:content>Завершение</v8:content>
					</v8:item>
				</Title>
				<ToolTip/>
				<TabOrder>1</TabOrder>
				<BackColor>auto</BackColor>
				<TextColor>style:FormTextColor</TextColor>
				<LineColor>style:BorderColor</LineColor>
				<GroupNumber>0</GroupNumber>
				<ZOrder>0</ZOrder>
				<Hyperlink>false</Hyperlink>
				<Transparent>false</Transparent>
				<Font kind="AutoFont"/>
				<HorizontalAlign>Center</HorizontalAlign>
				<VerticalAlign>Center</VerticalAlign>
				<PictureLocation>Left</PictureLocation>
				<Location top="580" left="1160" bottom="660" right="1280"/>
				<Border width="1" gap="false">
					<v8ui:style xsi:type="sch:ConnectorLineType">Solid</v8ui:style>
				</Border>
				<Picture/>
				<PictureSize>AutoSize</PictureSize>
			</Properties>
			<Events>
				<Event name="OnComplete"/>
			</Events>
		</Completion>
		<Start id="2" uuid="ebf99e66-3b13-4b2f-ae50-a80847f2e88c">
			<Properties>
				<Name>Старт</Name>
				<Title>
					<v8:item>
						<v8:lang>ru</v8:lang>
						<v8:content>Старт</v8:content>
					</v8:item>
				</Title>
				<ToolTip/>
				<TabOrder>2</TabOrder>
				<BackColor>auto</BackColor>
				<TextColor>style:FormTextColor</TextColor>
				<LineColor>style:BorderColor</LineColor>
				<GroupNumber>0</GroupNumber>
				<ZOrder>1</ZOrder>
				<Hyperlink>false</Hyperlink>
				<Transparent>false</Transparent>
				<Font kind="AutoFont"/>
				<HorizontalAlign>Center</HorizontalAlign>
				<VerticalAlign>Center</VerticalAlign>
				<PictureLocation>Left</PictureLocation>
				<Location top="60" left="560" bottom="140" right="680"/>
				<Border width="1" gap="false">
					<v8ui:style xsi:type="sch:ConnectorLineType">Solid</v8ui:style>
				</Border>
				<Picture/>
				<PictureSize>AutoSize</PictureSize>
			</Properties>
			<Events>
				<Event name="BeforeStart"/>
			</Events>
		</Start>
		<ConnectionLine id="3">
			<Properties>
				<Name>Линия1</Name>
				<Title/>
				<ToolTip/>
				<TabOrder>3</TabOrder>
				<BackColor>auto</BackColor>
				<TextColor>style:FormTextColor</TextColor>
				<LineColor>style:BorderColor</LineColor>
				<GroupNumber>0</GroupNumber>
				<ZOrder>2</ZOrder>
				<Hyperlink>false</Hyperlink>
				<Transparent>false</Transparent>
				<Font kind="AutoFont"/>
				<HorizontalAlign>Center</HorizontalAlign>
				<VerticalAlign>Center</VerticalAlign>
				<PictureLocation>Left</PictureLocation>
				<PivotPoints>
					<Point x="620" y="140"/>
					<Point x="620" y="160"/>
					<Point x="620" y="160"/>
					<Point x="620" y="180"/>
				</PivotPoints>
				<Connect>
					<From>
						<Item>Старт</Item>
						<PortIndex>4</PortIndex>
					</From>
					<To>
						<Item>ПрикрепитьДокументы</Item>
						<PortIndex>2</PortIndex>
					</To>
				</Connect>
				<Line width="1" gap="false">
					<v8ui:style xsi:type="sch:ConnectorLineType">Solid</v8ui:style>
				</Line>
				<DecorativeLine>false</DecorativeLine>
				<TextLocation>FirstSegment</TextLocation>
				<BeginArrow>None</BeginArrow>
				<EndArrow>Filled</EndArrow>
			</Properties>
		</ConnectionLine>
		<Activity id="4" uuid="14cbd04d-fe0d-4e50-9745-7d88b7f7e218">
			<Properties>
				<Name>ПрикрепитьДокументы</Name>
				<Title>
					<v8:item>
						<v8:lang>ru</v8:lang>
						<v8:content>Прикрепить документы</v8:content>
					</v8:item>
				</Title>
				<ToolTip/>
				<TabOrder>5</TabOrder>
				<BackColor>auto</BackColor>
				<TextColor>style:FormTextColor</TextColor>
				<LineColor>style:BorderColor</LineColor>
				<GroupNumber>0</GroupNumber>
				<ZOrder>3</ZOrder>
				<Hyperlink>false</Hyperlink>
				<Transparent>false</Transparent>
				<Font kind="AutoFont"/>
				<HorizontalAlign>Center</HorizontalAlign>
				<VerticalAlign>Center</VerticalAlign>
				<PictureLocation>Left</PictureLocation>
				<Location top="180" left="540" bottom="260" right="700"/>
				<Border width="1" gap="false">
					<v8ui:style xsi:type="sch:ConnectorLineType">Solid</v8ui:style>
				</Border>
				<Picture/>
				<PictureSize>AutoSize</PictureSize>
				<TaskDescription>Прикрепить документы</TaskDescription>
				<Explanation/>
				<Group>false</Group>
				<AddressingAttributes>
					<AddressingAttribute ref="Task.бестЗадачаДоговорногоБлока.AddressingAttribute.Исполнитель">
						<Value xsi:nil="true"/>
					</AddressingAttribute>
					<AddressingAttribute ref="Task.бестЗадачаДоговорногоБлока.AddressingAttribute.Организация">
						<Value xsi:nil="true"/>
					</AddressingAttribute>
					<AddressingAttribute ref="Task.бестЗадачаДоговорногоБлока.AddressingAttribute.Роль">
						<Value xsi:nil="true"/>
					</AddressingAttribute>
				</AddressingAttributes>
			</Properties>
			<Events>
				<Event name="InteractiveActivationProcessing"/>
				<Event name="BeforeCreateTasks"/>
				<Event name="OnCreateTask">ПриСозданииЗадач</Event>
				<Event name="OnExecute">ПриВыполнении</Event>
				<Event name="CheckExecutionProcessing"/>
				<Event name="BeforeExecute"/>
				<Event name="BeforeExecuteInteractively"/>
			</Events>
		</Activity>
		<ConnectionLine id="5">
			<Properties>
				<Name>Линия2</Name>
				<Title/>
				<ToolTip/>
				<TabOrder>6</TabOrder>
				<BackColor>auto</BackColor>
				<TextColor>style:FormTextColor</TextColor>
				<LineColor>style:BorderColor</LineColor>
				<GroupNumber>0</GroupNumber>
				<ZOrder>4</ZOrder>
				<Hyperlink>false</Hyperlink>
				<Transparent>false</Transparent>
				<Font kind="AutoFont"/>
				<HorizontalAlign>Center</HorizontalAlign>
				<VerticalAlign>Center</VerticalAlign>
				<PictureLocation>Left</PictureLocation>
				<PivotPoints>
					<Point x="620" y="260"/>
					<Point x="620" y="280"/>
					<Point x="620" y="280"/>
					<Point x="620" y="300"/>
				</PivotPoints>
				<Connect>
					<From>
						<Item>ПрикрепитьДокументы</Item>
						<PortIndex>4</PortIndex>
					</From>
					<To>
						<Item>РешениеЗаключенииДоговора</Item>
						<PortIndex>2</PortIndex>
					</To>
				</Connect>
				<Line width="1" gap="false">
					<v8ui:style xsi:type="sch:ConnectorLineType">Solid</v8ui:style>
				</Line>
				<DecorativeLine>false</DecorativeLine>
				<TextLocation>FirstSegment</TextLocation>
				<BeginArrow>None</BeginArrow>
				<EndArrow>Filled</EndArrow>
			</Properties>
		</ConnectionLine>
		<Activity id="9" uuid="88eebf8d-0211-4bb0-8435-1a4b1665ce48">
			<Properties>
				<Name>НаправитьУведомлениеОбОтсутствииДокументов</Name>
				<Title>
					<v8:item>
						<v8:lang>ru</v8:lang>
						<v8:content>Направить уведомления об отсутствии документов</v8:content>
					</v8:item>
				</Title>
				<ToolTip/>
				<TabOrder>32</TabOrder>
				<BackColor>auto</BackColor>
				<TextColor>style:FormTextColor</TextColor>
				<LineColor>style:BorderColor</LineColor>
				<GroupNumber>0</GroupNumber>
				<ZOrder>5</ZOrder>
				<Hyperlink>false</Hyperlink>
				<Transparent>false</Transparent>
				<Font kind="AutoFont"/>
				<HorizontalAlign>Center</HorizontalAlign>
				<VerticalAlign>Center</VerticalAlign>
				<PictureLocation>Left</PictureLocation>
				<Location top="420" left="740" bottom="500" right="900"/>
				<Border width="1" gap="false">
					<v8ui:style xsi:type="sch:ConnectorLineType">Solid</v8ui:style>
				</Border>
				<Picture/>
				<PictureSize>AutoSize</PictureSize>
				<TaskDescription>Направить уведомления об отсутствии документов</TaskDescription>
				<Explanation/>
				<Group>false</Group>
				<AddressingAttributes>
					<AddressingAttribute ref="Task.бестЗадачаДоговорногоБлока.AddressingAttribute.Исполнитель">
						<Value xsi:nil="true"/>
					</AddressingAttribute>
					<AddressingAttribute ref="Task.бестЗадачаДоговорногоБлока.AddressingAttribute.Организация">
						<Value xsi:nil="true"/>
					</AddressingAttribute>
					<AddressingAttribute ref="Task.бестЗадачаДоговорногоБлока.AddressingAttribute.Роль">
						<Value xsi:nil="true"/>
					</AddressingAttribute>
				</AddressingAttributes>
			</Properties>
			<Events>
				<Event name="InteractiveActivationProcessing"/>
				<Event name="BeforeCreateTasks"/>
				<Event name="OnCreateTask">ПриСозданииЗадач</Event>
				<Event name="OnExecute">ПриВыполнении</Event>
				<Event name="CheckExecutionProcessing"/>
				<Event name="BeforeExecute"/>
				<Event name="BeforeExecuteInteractively"/>
			</Events>
		</Activity>
		<ConnectionLine id="10">
			<Properties>
				<Name>Линия5</Name>
				<Title/>
				<ToolTip/>
				<TabOrder>33</TabOrder>
				<BackColor>auto</BackColor>
				<TextColor>style:FormTextColor</TextColor>
				<LineColor>style:BorderColor</LineColor>
				<GroupNumber>0</GroupNumber>
				<ZOrder>6</ZOrder>
				<Hyperlink>false</Hyperlink>
				<Transparent>false</Transparent>
				<Font kind="AutoFont"/>
				<HorizontalAlign>Center</HorizontalAlign>
				<VerticalAlign>Center</VerticalAlign>
				<PictureLocation>Left</PictureLocation>
				<PivotPoints>
					<Point x="820" y="500"/>
					<Point x="820" y="520"/>
					<Point x="820" y="520"/>
					<Point x="820" y="540"/>
				</PivotPoints>
				<Connect>
					<From>
						<Item>НаправитьУведомлениеОбОтсутствииДокументов</Item>
						<PortIndex>4</PortIndex>
					</From>
					<To>
						<Item>ПолучениеДопДокументов</Item>
						<PortIndex>2</PortIndex>
					</To>
				</Connect>
				<Line width="1" gap="false">
					<v8ui:style xsi:type="sch:ConnectorLineType">Solid</v8ui:style>
				</Line>
				<DecorativeLine>false</DecorativeLine>
				<TextLocation>FirstSegment</TextLocation>
				<BeginArrow>None</BeginArrow>
				<EndArrow>Filled</EndArrow>
			</Properties>
		</ConnectionLine>
		<Activity id="11" uuid="a57eacd3-e6dc-4905-8c9d-3fe4ae885305">
			<Properties>
				<Name>ПолучениеДопДокументов</Name>
				<Title>
					<v8:item>
						<v8:lang>ru</v8:lang>
						<v8:content>Зарегистрировать получение доп. документов</v8:content>
					</v8:item>
				</Title>
				<ToolTip/>
				<TabOrder>34</TabOrder>
				<BackColor>auto</BackColor>
				<TextColor>style:FormTextColor</TextColor>
				<LineColor>style:BorderColor</LineColor>
				<GroupNumber>0</GroupNumber>
				<ZOrder>7</ZOrder>
				<Hyperlink>false</Hyperlink>
				<Transparent>false</Transparent>
				<Font kind="AutoFont"/>
				<HorizontalAlign>Center</HorizontalAlign>
				<VerticalAlign>Center</VerticalAlign>
				<PictureLocation>Left</PictureLocation>
				<Location top="540" left="740" bottom="620" right="900"/>
				<Border width="1" gap="false">
					<v8ui:style xsi:type="sch:ConnectorLineType">Solid</v8ui:style>
				</Border>
				<Picture/>
				<PictureSize>AutoSize</PictureSize>
				<TaskDescription>Зарегистрировать получение доп. документов</TaskDescription>
				<Explanation/>
				<Group>false</Group>
				<AddressingAttributes>
					<AddressingAttribute ref="Task.бестЗадачаДоговорногоБлока.AddressingAttribute.Исполнитель">
						<Value xsi:nil="true"/>
					</AddressingAttribute>
					<AddressingAttribute ref="Task.бестЗадачаДоговорногоБлока.AddressingAttribute.Организация">
						<Value xsi:nil="true"/>
					</AddressingAttribute>
					<AddressingAttribute ref="Task.бестЗадачаДоговорногоБлока.AddressingAttribute.Роль">
						<Value xsi:nil="true"/>
					</AddressingAttribute>
				</AddressingAttributes>
			</Properties>
			<Events>
				<Event name="InteractiveActivationProcessing"/>
				<Event name="BeforeCreateTasks"/>
				<Event name="OnCreateTask">ПриСозданииЗадач</Event>
				<Event name="OnExecute">ПриВыполнении</Event>
				<Event name="CheckExecutionProcessing"/>
				<Event name="BeforeExecute"/>
				<Event name="BeforeExecuteInteractively"/>
			</Events>
		</Activity>
		<ConnectionLine id="12">
			<Properties>
				<Name>Линия6</Name>
				<Title/>
				<ToolTip/>
				<TabOrder>35</TabOrder>
				<BackColor>auto</BackColor>
				<TextColor>style:FormTextColor</TextColor>
				<LineColor>style:BorderColor</LineColor>
				<GroupNumber>0</GroupNumber>
				<ZOrder>8</ZOrder>
				<Hyperlink>false</Hyperlink>
				<Transparent>false</Transparent>
				<Font kind="AutoFont"/>
				<HorizontalAlign>Center</HorizontalAlign>
				<VerticalAlign>Center</VerticalAlign>
				<PictureLocation>Left</PictureLocation>
				<PivotPoints>
					<Point x="740" y="580"/>
					<Point x="520" y="580"/>
					<Point x="520" y="220"/>
					<Point x="540" y="220"/>
				</PivotPoints>
				<Connect>
					<From>
						<Item>ПолучениеДопДокументов</Item>
						<PortIndex>1</PortIndex>
					</From>
					<To>
						<Item>ПрикрепитьДокументы</Item>
						<PortIndex>1</PortIndex>
					</To>
				</Connect>
				<Line width="1" gap="false">
					<v8ui:style xsi:type="sch:ConnectorLineType">Solid</v8ui:style>
				</Line>
				<DecorativeLine>false</DecorativeLine>
				<TextLocation>FirstSegment</TextLocation>
				<BeginArrow>None</BeginArrow>
				<EndArrow>Filled</EndArrow>
			</Properties>
		</ConnectionLine>
		<Switch id="15" uuid="de8c49dd-8c52-4f1c-b9cc-39aae2bbd7d2">
			<Properties>
				<Name>РешениеЗаключенииДоговора</Name>
				<Title>
					<v8:item>
						<v8:lang>ru</v8:lang>
						<v8:content>Решение о заключении договора/ДС</v8:content>
					</v8:item>
				</Title>
				<ToolTip/>
				<TabOrder>36</TabOrder>
				<BackColor>auto</BackColor>
				<TextColor>style:FormTextColor</TextColor>
				<LineColor>style:BorderColor</LineColor>
				<GroupNumber>0</GroupNumber>
				<ZOrder>9</ZOrder>
				<Hyperlink>false</Hyperlink>
				<Transparent>false</Transparent>
				<Font kind="AutoFont"/>
				<HorizontalAlign>Center</HorizontalAlign>
				<VerticalAlign>Center</VerticalAlign>
				<PictureLocation>Left</PictureLocation>
				<Location top="300" left="540" bottom="400" right="700"/>
				<Border width="1" gap="false">
					<v8ui:style xsi:type="sch:ConnectorLineType">Solid</v8ui:style>
				</Border>
				<Picture/>
				<PictureSize>AutoSize</PictureSize>
				<Case>
					<sch:name>ПолныйПакетДокументов</sch:name>
					<sch:description>
						<v8:item>
							<v8:lang>ru</v8:lang>
							<v8:content>Полный пакет документов</v8:content>
						</v8:item>
					</sch:description>
					<sch:backColor>auto</sch:backColor>
				</Case>
				<Case>
					<sch:name>ОтказВЗаключении</sch:name>
					<sch:description>
						<v8:item>
							<v8:lang>ru</v8:lang>
							<v8:content>Отказ в заключении</v8:content>
						</v8:item>
					</sch:description>
					<sch:backColor>auto</sch:backColor>
				</Case>
				<Case>
					<sch:name>НеполныйПакетДокументов</sch:name>
					<sch:description>
						<v8:item>
							<v8:lang>ru</v8:lang>
							<v8:content>Неполный пакет документов</v8:content>
						</v8:item>
					</sch:description>
					<sch:backColor>auto</sch:backColor>
				</Case>
			</Properties>
			<Events>
				<Event name="SwitchProcessing">ПроверкаУсловия</Event>
			</Events>
		</Switch>
		<ConnectionLine id="16">
			<Properties>
				<Name>Линия7</Name>
				<Title/>
				<ToolTip/>
				<TabOrder>37</TabOrder>
				<BackColor>auto</BackColor>
				<TextColor>style:FormTextColor</TextColor>
				<LineColor>style:BorderColor</LineColor>
				<GroupNumber>0</GroupNumber>
				<ZOrder>10</ZOrder>
				<Hyperlink>false</Hyperlink>
				<Transparent>false</Transparent>
				<Font kind="AutoFont"/>
				<HorizontalAlign>Center</HorizontalAlign>
				<VerticalAlign>Center</VerticalAlign>
				<PictureLocation>Left</PictureLocation>
				<PivotPoints>
					<Point x="699" y="354"/>
					<Point x="1220" y="354"/>
					<Point x="1220" y="420"/>
				</PivotPoints>
				<Connect>
					<From>
						<Item>РешениеЗаключенииДоговора</Item>
						<PortIndex>7</PortIndex>
					</From>
					<To>
						<Item>ПодготовитьПроектаДоговора</Item>
						<PortIndex>2</PortIndex>
					</To>
				</Connect>
				<Line width="1" gap="false">
					<v8ui:style xsi:type="sch:ConnectorLineType">Solid</v8ui:style>
				</Line>
				<DecorativeLine>false</DecorativeLine>
				<TextLocation>FirstSegment</TextLocation>
				<BeginArrow>None</BeginArrow>
				<EndArrow>Filled</EndArrow>
			</Properties>
		</ConnectionLine>
		<ConnectionLine id="17">
			<Properties>
				<Name>Линия8</Name>
				<Title/>
				<ToolTip/>
				<TabOrder>38</TabOrder>
				<BackColor>auto</BackColor>
				<TextColor>style:FormTextColor</TextColor>
				<LineColor>style:BorderColor</LineColor>
				<GroupNumber>0</GroupNumber>
				<ZOrder>11</ZOrder>
				<Hyperlink>false</Hyperlink>
				<Transparent>false</Transparent>
				<Font kind="AutoFont"/>
				<HorizontalAlign>Center</HorizontalAlign>
				<VerticalAlign>Center</VerticalAlign>
				<PictureLocation>Left</PictureLocation>
				<PivotPoints>
					<Point x="699" y="372"/>
					<Point x="1020" y="372"/>
					<Point x="1020" y="420"/>
				</PivotPoints>
				<Connect>
					<From>
						<Item>РешениеЗаключенииДоговора</Item>
						<PortIndex>9</PortIndex>
					</From>
					<To>
						<Item>УведомлениеОбОтказе</Item>
						<PortIndex>2</PortIndex>
					</To>
				</Connect>
				<Line width="1" gap="false">
					<v8ui:style xsi:type="sch:ConnectorLineType">Solid</v8ui:style>
				</Line>
				<DecorativeLine>false</DecorativeLine>
				<TextLocation>FirstSegment</TextLocation>
				<BeginArrow>None</BeginArrow>
				<EndArrow>Filled</EndArrow>
			</Properties>
		</ConnectionLine>
		<ConnectionLine id="18">
			<Properties>
				<Name>Линия9</Name>
				<Title/>
				<ToolTip/>
				<TabOrder>39</TabOrder>
				<BackColor>auto</BackColor>
				<TextColor>style:FormTextColor</TextColor>
				<LineColor>style:BorderColor</LineColor>
				<GroupNumber>0</GroupNumber>
				<ZOrder>12</ZOrder>
				<Hyperlink>false</Hyperlink>
				<Transparent>false</Transparent>
				<Font kind="AutoFont"/>
				<HorizontalAlign>Center</HorizontalAlign>
				<VerticalAlign>Center</VerticalAlign>
				<PictureLocation>Left</PictureLocation>
				<PivotPoints>
					<Point x="699" y="390"/>
					<Point x="820" y="390"/>
					<Point x="820" y="420"/>
				</PivotPoints>
				<Connect>
					<From>
						<Item>РешениеЗаключенииДоговора</Item>
						<PortIndex>11</PortIndex>
					</From>
					<To>
						<Item>НаправитьУведомлениеОбОтсутствииДокументов</Item>
						<PortIndex>2</PortIndex>
					</To>
				</Connect>
				<Line width="1" gap="false">
					<v8ui:style xsi:type="sch:ConnectorLineType">Solid</v8ui:style>
				</Line>
				<DecorativeLine>false</DecorativeLine>
				<TextLocation>FirstSegment</TextLocation>
				<BeginArrow>None</BeginArrow>
				<EndArrow>Filled</EndArrow>
			</Properties>
		</ConnectionLine>
		<Activity id="23" uuid="9522a80f-c37c-4a84-8ed1-546ae02e273f">
			<Properties>
				<Name>УведомлениеОбОтказе</Name>
				<Title>
					<v8:item>
						<v8:lang>ru</v8:lang>
						<v8:content>Направить уведомление об отказе в заключении договора/ДС</v8:content>
					</v8:item>
				</Title>
				<ToolTip/>
				<TabOrder>40</TabOrder>
				<BackColor>auto</BackColor>
				<TextColor>style:FormTextColor</TextColor>
				<LineColor>style:BorderColor</LineColor>
				<GroupNumber>0</GroupNumber>
				<ZOrder>13</ZOrder>
				<Hyperlink>false</Hyperlink>
				<Transparent>false</Transparent>
				<Font kind="AutoFont"/>
				<HorizontalAlign>Center</HorizontalAlign>
				<VerticalAlign>Center</VerticalAlign>
				<PictureLocation>Left</PictureLocation>
				<Location top="420" left="940" bottom="500" right="1100"/>
				<Border width="1" gap="false">
					<v8ui:style xsi:type="sch:ConnectorLineType">Solid</v8ui:style>
				</Border>
				<Picture/>
				<PictureSize>AutoSize</PictureSize>
				<TaskDescription>Направить уведомление об отказе в заключении договора/ДС</TaskDescription>
				<Explanation/>
				<Group>false</Group>
				<AddressingAttributes>
					<AddressingAttribute ref="Task.бестЗадачаДоговорногоБлока.AddressingAttribute.Исполнитель">
						<Value xsi:nil="true"/>
					</AddressingAttribute>
					<AddressingAttribute ref="Task.бестЗадачаДоговорногоБлока.AddressingAttribute.Организация">
						<Value xsi:nil="true"/>
					</AddressingAttribute>
					<AddressingAttribute ref="Task.бестЗадачаДоговорногоБлока.AddressingAttribute.Роль">
						<Value xsi:nil="true"/>
					</AddressingAttribute>
				</AddressingAttributes>
			</Properties>
			<Events>
				<Event name="InteractiveActivationProcessing"/>
				<Event name="BeforeCreateTasks"/>
				<Event name="OnCreateTask">ПриСозданииЗадач</Event>
				<Event name="OnExecute">ПриВыполнении</Event>
				<Event name="CheckExecutionProcessing"/>
				<Event name="BeforeExecute"/>
				<Event name="BeforeExecuteInteractively"/>
			</Events>
		</Activity>
		<ConnectionLine id="24">
			<Properties>
				<Name>Линия10</Name>
				<Title/>
				<ToolTip/>
				<TabOrder>41</TabOrder>
				<BackColor>auto</BackColor>
				<TextColor>style:FormTextColor</TextColor>
				<LineColor>style:BorderColor</LineColor>
				<GroupNumber>0</GroupNumber>
				<ZOrder>14</ZOrder>
				<Hyperlink>false</Hyperlink>
				<Transparent>false</Transparent>
				<Font kind="AutoFont"/>
				<HorizontalAlign>Center</HorizontalAlign>
				<VerticalAlign>Center</VerticalAlign>
				<PictureLocation>Left</PictureLocation>
				<PivotPoints>
					<Point x="1020" y="500"/>
					<Point x="1020" y="540"/>
					<Point x="1220" y="540"/>
					<Point x="1220" y="580"/>
				</PivotPoints>
				<Connect>
					<From>
						<Item>УведомлениеОбОтказе</Item>
						<PortIndex>4</PortIndex>
					</From>
					<To>
						<Item>Завершение</Item>
						<PortIndex>2</PortIndex>
					</To>
				</Connect>
				<Line width="1" gap="false">
					<v8ui:style xsi:type="sch:ConnectorLineType">Solid</v8ui:style>
				</Line>
				<DecorativeLine>false</DecorativeLine>
				<TextLocation>FirstSegment</TextLocation>
				<BeginArrow>None</BeginArrow>
				<EndArrow>Filled</EndArrow>
			</Properties>
		</ConnectionLine>
		<SubBusinessProcess id="27" uuid="a94112a9-cc75-4b71-855c-a6ea2fa05055">
			<Properties>
				<Name>ПодготовитьПроектаДоговора</Name>
				<Title>
					<v8:item>
						<v8:lang>ru</v8:lang>
						<v8:content>Подготовить проекта договора/ДС</v8:content>
					</v8:item>
				</Title>
				<ToolTip/>
				<TabOrder>44</TabOrder>
				<BackColor>auto</BackColor>
				<TextColor>style:FormTextColor</TextColor>
				<LineColor>style:BorderColor</LineColor>
				<GroupNumber>0</GroupNumber>
				<ZOrder>15</ZOrder>
				<Hyperlink>false</Hyperlink>
				<Transparent>false</Transparent>
				<Font kind="AutoFont"/>
				<HorizontalAlign>Center</HorizontalAlign>
				<VerticalAlign>Center</VerticalAlign>
				<PictureLocation>Left</PictureLocation>
				<Location top="420" left="1140" bottom="500" right="1300"/>
				<Border width="1" gap="false">
					<v8ui:style xsi:type="sch:ConnectorLineType">Solid</v8ui:style>
				</Border>
				<Picture/>
				<PictureSize>AutoSize</PictureSize>
				<Subprocess>BusinessProcess.бестПодготовкаПроектаДоговора</Subprocess>
				<TaskDescription>Подготовить проекта договора/ДС</TaskDescription>
			</Properties>
			<Events>
				<Event name="BeforeCreateTasks"/>
				<Event name="OnCreateTask">ПриСозданииЗадач</Event>
				<Event name="OnCreateSubBusinessProcesses">ПриСозданииВложенныхБизнесПроцессов</Event>
				<Event name="OnExecute"/>
				<Event name="BeforeExecute"/>
				<Event name="BeforeCreateSubBusinessProcesses"/>
			</Events>
		</SubBusinessProcess>
		<ConnectionLine id="28">
			<Properties>
				<Name>Линия3</Name>
				<Title/>
				<ToolTip/>
				<TabOrder>45</TabOrder>
				<BackColor>auto</BackColor>
				<TextColor>style:FormTextColor</TextColor>
				<LineColor>style:BorderColor</LineColor>
				<GroupNumber>0</GroupNumber>
				<ZOrder>16</ZOrder>
				<Hyperlink>false</Hyperlink>
				<Transparent>false</Transparent>
				<Font kind="AutoFont"/>
				<HorizontalAlign>Center</HorizontalAlign>
				<VerticalAlign>Center</VerticalAlign>
				<PictureLocation>Left</PictureLocation>
				<PivotPoints>
					<Point x="1220" y="500"/>
					<Point x="1220" y="540"/>
					<Point x="1220" y="540"/>
					<Point x="1220" y="580"/>
				</PivotPoints>
				<Connect>
					<From>
						<Item>ПодготовитьПроектаДоговора</Item>
						<PortIndex>4</PortIndex>
					</From>
					<To>
						<Item>Завершение</Item>
						<PortIndex>2</PortIndex>
					</To>
				</Connect>
				<Line width="1" gap="false">
					<v8ui:style xsi:type="sch:ConnectorLineType">Solid</v8ui:style>
				</Line>
				<DecorativeLine>false</DecorativeLine>
				<TextLocation>FirstSegment</TextLocation>
				<BeginArrow>None</BeginArrow>
				<EndArrow>Filled</EndArrow>
			</Properties>
		</ConnectionLine>
	</Items>
</GraphicalSchema>